{
  "id": "d007d292-fd13-42c7-bbd7-10448fb58136",
  "uid": "provident-quia-soluta",
  "type": "trending",
  "data": {
    "info": [
      {
        "type": "heading1",
        "text": "Utilize clicks-and-mortar applications",
        "spans": []
      }
    ],
    "headline": [
      {
        "type": "paragraph",
        "text": "Ex nisi labore nostrud adipisicing mollit veniam eiusmod excepteur culpa do laboris. Sint incididunt duis cupidatat Lorem non commodo elit. Et mollit ex tempor dolor cupidatat deserunt incididunt anim officia laborum officia voluptate.",
        "spans": []
      }
    ]
  }
}